good_supabase/__init__.py
good_supabase/_auth.py
good_supabase/_client.py
good_supabase/_realtime.py
good_supabase-0.1.7.dist-info/METADATA
good_supabase-0.1.7.dist-info/WHEEL
good_supabase-0.1.7.dist-info/RECORD
