Metadata-Version: 2.4
Name: good-supabase
Version: 0.1.7
Summary: Add your description here
Author-email: Chris Goddard <chris@goodkiwi.llc>
Requires-Python: >=3.12
Requires-Dist: good-common
Requires-Dist: supabase>=2.7.3
Requires-Dist: tenacity>=8.5.0
